[[1.022814,{"lines":{"0":[["                                                                                  ",{}]],"1":[["                                                                                  ",{}]],"2":[["                                                                                  ",{}]],"3":[["                                                                                  ",{}]],"4":[["                                                                                  ",{}]],"5":[["                                                                                  ",{}]],"6":[["                                                                                  ",{}]],"7":[["                                                                                  ",{}]],"8":[["                                                                                  ",{}]],"9":[["                                                                                  ",{}]],"10":[["                                                                                  ",{}]],"11":[["                                                                                  ",{}]],"12":[["                                                                                  ",{}]],"13":[["                                                                                  ",{}]],"14":[["                                                                                  ",{}]],"15":[["                                                                                  ",{}]],"16":[["                                                                                  ",{}]],"17":[["                                                                                  ",{}]],"18":[["                                                                                  ",{}]],"19":[["                                                                                  ",{}]],"20":[["                                                                                  ",{}]]},"cursor":{"x":0,"y":0,"visible":true}}],[0.000296,{"lines":{"0":[["cai@gentoo",{"fg":2,"bold":true}],[" ~ $",{"fg":4,"bold":true}],["                                                                    ",{}]]},"cursor":{"x":15}}],[0.351472,{"lines":{"0":[["cai@gentoo",{"fg":2,"bold":true}],[" ~ $",{"fg":4,"bold":true}],[" sudo emerge wineqq -av                                             ",{}]]},"cursor":{"x":37}}],[1.232233,{"cursor":{"x":38}}],[0.175965,{"lines":{"0":[["cai@gentoo",{"fg":2,"bold":true}],[" ~ $",{"fg":4,"bold":true}],[" sudo emerge wineqq -av -                                           ",{}]]},"cursor":{"x":39}}],[0.143871,{"lines":{"0":[["cai@gentoo",{"fg":2,"bold":true}],[" ~ $",{"fg":4,"bold":true}],[" sudo emerge wineqq -av --                                          ",{}]]},"cursor":{"x":40}}],[0.191932,{"lines":{"0":[["cai@gentoo",{"fg":2,"bold":true}],[" ~ $",{"fg":4,"bold":true}],[" sudo emerge wineqq -av --q                                         ",{}]]},"cursor":{"x":41}}],[0.352151,{"lines":{"0":[["cai@gentoo",{"fg":2,"bold":true}],[" ~ $",{"fg":4,"bold":true}],[" sudo emerge wineqq -av --qu                                        ",{}]]},"cursor":{"x":42}}],[0.199998,{"lines":{"0":[["cai@gentoo",{"fg":2,"bold":true}],[" ~ $",{"fg":4,"bold":true}],[" sudo emerge wineqq -av --qui                                       ",{}]]},"cursor":{"x":43}}],[0.223578,{"lines":{"0":[["cai@gentoo",{"fg":2,"bold":true}],[" ~ $",{"fg":4,"bold":true}],[" sudo emerge wineqq -av --quie                                      ",{}]]},"cursor":{"x":44}}],[0.244796,{"lines":{"0":[["cai@gentoo",{"fg":2,"bold":true}],[" ~ $",{"fg":4,"bold":true}],[" sudo emerge wineqq -av --quiet                                     ",{}]]},"cursor":{"x":45}}],[0.299535,{"lines":{"0":[["cai@gentoo",{"fg":2,"bold":true}],[" ~ $",{"fg":4,"bold":true}],[" sudo emerge wineqq -av --quiet-                                    ",{}]]},"cursor":{"x":46}}],[0.191962,{"lines":{"0":[["cai@gentoo",{"fg":2,"bold":true}],[" ~ $",{"fg":4,"bold":true}],[" sudo emerge wineqq -av --quiet-b                                   ",{}]]},"cursor":{"x":47}}],[0.168027,{"lines":{"0":[["cai@gentoo",{"fg":2,"bold":true}],[" ~ $",{"fg":4,"bold":true}],[" sudo emerge wineqq -av --quiet-bu                                  ",{}]]},"cursor":{"x":48}}],[0.095917,{"lines":{"0":[["cai@gentoo",{"fg":2,"bold":true}],[" ~ $",{"fg":4,"bold":true}],[" sudo emerge wineqq -av --quiet-bui                                 ",{}]]},"cursor":{"x":49}}],[0.144111,{"lines":{"0":[["cai@gentoo",{"fg":2,"bold":true}],[" ~ $",{"fg":4,"bold":true}],[" sudo emerge wineqq -av --quiet-buil                                ",{}]]},"cursor":{"x":50}}],[0.087898,{"lines":{"0":[["cai@gentoo",{"fg":2,"bold":true}],[" ~ $",{"fg":4,"bold":true}],[" sudo emerge wineqq -av --quiet-build                               ",{}]]},"cursor":{"x":51}}],[0.424205,{"lines":{"0":[["cai@gentoo",{"fg":2,"bold":true}],[" ~ $",{"fg":4,"bold":true}],[" sudo emerge wineqq -av --quiet-build-                              ",{}]]},"cursor":{"x":52}}],[0.287892,{"lines":{"0":[["cai@gentoo",{"fg":2,"bold":true}],[" ~ $",{"fg":4,"bold":true}],[" sudo emerge wineqq -av --quiet-build-n                             ",{}]]},"cursor":{"x":53}}],[0.304142,{"lines":{"0":[["cai@gentoo",{"fg":2,"bold":true}],[" ~ $",{"fg":4,"bold":true}],[" sudo emerge wineqq -av --quiet-build-                              ",{}]]},"cursor":{"x":52}}],[0.167909,{"lines":{"0":[["cai@gentoo",{"fg":2,"bold":true}],[" ~ $",{"fg":4,"bold":true}],[" sudo emerge wineqq -av --quiet-build-=                             ",{}]]},"cursor":{"x":53}}],[0.5278890000000001,{"lines":{"0":[["cai@gentoo",{"fg":2,"bold":true}],[" ~ $",{"fg":4,"bold":true}],[" sudo emerge wineqq -av --quiet-build-==                            ",{}]]},"cursor":{"x":54}}],[0.143976,{"lines":{"0":[["cai@gentoo",{"fg":2,"bold":true}],[" ~ $",{"fg":4,"bold":true}],[" sudo emerge wineqq -av --quiet-build-===                           ",{}]]},"cursor":{"x":55}}],[0.07997799999999999,{"lines":{"0":[["cai@gentoo",{"fg":2,"bold":true}],[" ~ $",{"fg":4,"bold":true}],[" sudo emerge wineqq -av --quiet-build-==                            ",{}]]},"cursor":{"x":54}}],[0.232049,{"lines":{"0":[["cai@gentoo",{"fg":2,"bold":true}],[" ~ $",{"fg":4,"bold":true}],[" sudo emerge wineqq -av --quiet-build-=                             ",{}]]},"cursor":{"x":53}}],[0.128023,{"lines":{"0":[["cai@gentoo",{"fg":2,"bold":true}],[" ~ $",{"fg":4,"bold":true}],[" sudo emerge wineqq -av --quiet-build-                              ",{}]]},"cursor":{"x":52}}],[0.159962,{"lines":{"0":[["cai@gentoo",{"fg":2,"bold":true}],[" ~ $",{"fg":4,"bold":true}],[" sudo emerge wineqq -av --quiet-build                               ",{}]]},"cursor":{"x":51}}],[0.007896,{"lines":{"0":[["cai@gentoo",{"fg":2,"bold":true}],[" ~ $",{"fg":4,"bold":true}],[" sudo emerge wineqq -av --quiet-build=                              ",{}]]},"cursor":{"x":52}}],[0.94426,{"lines":{"0":[["cai@gentoo",{"fg":2,"bold":true}],[" ~ $",{"fg":4,"bold":true}],[" sudo emerge wineqq -av --quiet-build=n                             ",{}]]},"cursor":{"x":53}}],[0.384253,{"cursor":{"x":0,"y":1}}],[0.003481,{"lines":{"1":[["密码：                                                                            ",{}]]},"cursor":{"x":6}}],[0.020003,{"cursor":{"x":0,"y":2}}],[1.584161,{"lines":{"2":[["Sorry, try again.                                                                 ",{}]],"3":[["密码：                                                                            ",{}]]},"cursor":{"x":6,"y":3}}],[0.974784,{"cursor":{"x":0,"y":4}}],[0.489779,{}],[0.038464,{"lines":{"5":[["These are the packages that would be merged, in order:",{"fg":2}],["                            ",{}]],"7":[["Calculating dependencies                                                          ",{}]]},"cursor":{"x":26,"y":7}}],[0.79905,{"lines":{"7":[["Calculating dependencies ",{}],[" G",{"fg":2,"bold":true}],["                                                       ",{}]]},"cursor":{"x":27}}],[0.050334,{"lines":{"7":[["Calculating dependencies ",{}],["  e",{"fg":2,"bold":true}],["                                                      ",{}]]},"cursor":{"x":28}}],[0.053342,{"lines":{"7":[["Calculating dependencies ",{}],["   n",{"fg":2,"bold":true}],["                                                     ",{}]]},"cursor":{"x":29}}],[0.04999,{"lines":{"7":[["Calculating dependencies ",{}],["    t",{"fg":2,"bold":true}],["                                                    ",{}]]},"cursor":{"x":30}}],[0.050195,{"lines":{"7":[["Calculating dependencies ",{}],["     o",{"fg":2,"bold":true}],["                                                   ",{}]]},"cursor":{"x":31}}],[0.050069,{"lines":{"7":[["Calculating dependencies ",{}],["      o",{"fg":2,"bold":true}],["                                                  ",{}]]},"cursor":{"x":32}}],[0.053039,{"lines":{"7":[["Calculating dependencies ",{}],["        ",{"fg":2,"bold":true}],["                                                 ",{}]]},"cursor":{"x":33}}],[0.05,{"lines":{"7":[["Calculating dependencies ",{}],["        R",{"fg":2,"bold":true}],["                                                ",{}]]},"cursor":{"x":34}}],[0.05012,{"lines":{"7":[["Calculating dependencies ",{}],["         o",{"fg":2,"bold":true}],["                                               ",{}]]},"cursor":{"x":35}}],[0.052077,{"lines":{"7":[["Calculating dependencies ",{}],["          c",{"fg":2,"bold":true}],["                                              ",{}]]},"cursor":{"x":36}}],[0.215635,{"lines":{"7":[["Calculating dependencies ",{}],["           k",{"fg":2,"bold":true}],["                                             ",{}]]},"cursor":{"x":37}}],[0.050905,{"lines":{"7":[["Calculating dependencies ",{}],["            s",{"fg":2,"bold":true}],["                                            ",{}]]},"cursor":{"x":38}}],[0.051803,{"lines":{"7":[["Calculating dependencies ",{}],["              ",{"fg":2,"bold":true}],["                                           ",{}]]},"cursor":{"x":39}}],[0.05048,{"lines":{"7":[["Calculating dependencies ",{}],["              (",{"fg":2,"bold":true}],["                                          ",{}]]},"cursor":{"x":40}}],[0.07742,{"lines":{"7":[["Calculating dependencies ",{}],["               L",{"fg":2,"bold":true}],["                                         ",{}]]},"cursor":{"x":41}}],[0.05252,{"lines":{"7":[["Calculating dependencies ",{}],["                i",{"fg":2,"bold":true}],["                                        ",{}]]},"cursor":{"x":42}}],[0.055444,{"lines":{"7":[["Calculating dependencies ",{}],["                 n",{"fg":2,"bold":true}],["                                       ",{}]]},"cursor":{"x":43}}],[0.051369,{"lines":{"7":[["Calculating dependencies ",{}],["                  u",{"fg":2,"bold":true}],["                                      ",{}]]},"cursor":{"x":44}}],[0.050006,{"lines":{"7":[["Calculating dependencies ",{}],["                   x",{"fg":2,"bold":true}],["                                     ",{}]]},"cursor":{"x":45}}],[0.052122,{"lines":{"7":[["Calculating dependencies ",{}],["                    )",{"fg":2,"bold":true}],["                                    ",{}]]},"cursor":{"x":46}}],[0.050165,{"lines":{"7":[["Calculating dependencies ",{}],["                   ",{"fg":2,"bold":true}],[")",{"fg":2}],[")",{"fg":2,"bold":true}],[" ",{"fg":2}],["                                   ",{}]]},"cursor":{"x":45}}],[0.050244,{"lines":{"7":[["Calculating dependencies ",{}],["                  ",{"fg":2,"bold":true}],["x)  ",{"fg":2}],["                                   ",{}]]},"cursor":{"x":44}}],[0.050674,{"lines":{"7":[["Calculating dependencies ",{}],["                 ",{"fg":2,"bold":true}],["ux   ",{"fg":2}],["                                   ",{}]]},"cursor":{"x":43}}],[0.052406,{"lines":{"7":[["Calculating dependencies ",{}],["                ",{"fg":2,"bold":true}],["nu    ",{"fg":2}],["                                   ",{}]]},"cursor":{"x":42}}],[0.050005,{"lines":{"7":[["Calculating dependencies ",{}],["               ",{"fg":2,"bold":true}],["in     ",{"fg":2}],["                                   ",{}]]},"cursor":{"x":41}}],[0.053167,{"lines":{"7":[["Calculating dependencies ",{}],["              ",{"fg":2,"bold":true}],["Li      ",{"fg":2}],["                                   ",{}]]},"cursor":{"x":40}}],[0.068372,{"lines":{"7":[["Calculating dependencies ",{}],["             ",{"fg":2,"bold":true}],["(L       ",{"fg":2}],["                                   ",{}]]},"cursor":{"x":39}}],[0.050942,{"lines":{"7":[["Calculating dependencies ",{}],["            ",{"fg":2,"bold":true}],[" (        ",{"fg":2}],["                                   ",{}]]},"cursor":{"x":38}}],[0.051246,{"lines":{"7":[["Calculating dependencies ",{}],["           ",{"fg":2,"bold":true}],["s          ",{"fg":2}],["                                   ",{}]]},"cursor":{"x":37}}],[0.050287,{"lines":{"7":[["Calculating dependencies ",{}],["          ",{"fg":2,"bold":true}],["ks          ",{"fg":2}],["                                   ",{}]]},"cursor":{"x":36}}],[0.052842,{"lines":{"7":[["Calculating dependencies ",{}],["         ",{"fg":2,"bold":true}],["ck           ",{"fg":2}],["                                   ",{}]]},"cursor":{"x":35}}],[0.050106,{"lines":{"7":[["Calculating dependencies ",{}],["        ",{"fg":2,"bold":true}],["oc            ",{"fg":2}],["                                   ",{}]]},"cursor":{"x":34}}],[0.051883,{"lines":{"7":[["Calculating dependencies ",{}],["       ",{"fg":2,"bold":true}],["Ro             ",{"fg":2}],["                                   ",{}]]},"cursor":{"x":33}}],[0.090591,{"lines":{"7":[["Calculating dependencies ",{}],["      ",{"fg":2,"bold":true}],[" R              ",{"fg":2}],["                                   ",{}]]},"cursor":{"x":32}}],[0.054926,{"lines":{"7":[["Calculating dependencies ",{}],["     ",{"fg":2,"bold":true}],["o                ",{"fg":2}],["                                   ",{}]]},"cursor":{"x":31}}],[0.055095,{"lines":{"7":[["Calculating dependencies ",{}],["    ",{"fg":2,"bold":true}],["oo                ",{"fg":2}],["                                   ",{}]]},"cursor":{"x":30}}],[0.050369,{"lines":{"7":[["Calculating dependencies ",{}],["   ",{"fg":2,"bold":true}],["to                 ",{"fg":2}],["                                   ",{}]]},"cursor":{"x":29}}],[0.050371,{"lines":{"7":[["Calculating dependencies ",{}],["  ",{"fg":2,"bold":true}],["nt                  ",{"fg":2}],["                                   ",{}]]},"cursor":{"x":28}}],[0.050083,{"lines":{"7":[["Calculating dependencies ",{}],[" ",{"fg":2,"bold":true}],["en                   ",{"fg":2}],["                                   ",{}]]},"cursor":{"x":27}}],[0.054246,{"lines":{"7":[["Calculating dependencies ",{}],["Ge                    ",{"fg":2}],["                                   ",{}]]},"cursor":{"x":26}}],[0.050745,{"lines":{"7":[["Calculating dependencies ",{}],[" G",{"fg":2,"bold":true}],["                    ",{"fg":2}],["                                   ",{}]]},"cursor":{"x":27}}],[0.050478,{"lines":{"7":[["Calculating dependencies ",{}],["  e",{"fg":2,"bold":true}],["                   ",{"fg":2}],["                                   ",{}]]},"cursor":{"x":28}}],[0.050583,{"lines":{"7":[["Calculating dependencies ",{}],["   n",{"fg":2,"bold":true}],["                  ",{"fg":2}],["                                   ",{}]]},"cursor":{"x":29}}],[0.052528,{"lines":{"7":[["Calculating dependencies ",{}],["    t",{"fg":2,"bold":true}],["                 ",{"fg":2}],["                                   ",{}]]},"cursor":{"x":30}}],[0.050202,{"lines":{"7":[["Calculating dependencies ",{}],["     o",{"fg":2,"bold":true}],["                ",{"fg":2}],["                                   ",{}]]},"cursor":{"x":31}}],[0.050223,{"lines":{"7":[["Calculating dependencies ",{}],["      o",{"fg":2,"bold":true}],["               ",{"fg":2}],["                                   ",{}]]},"cursor":{"x":32}}],[0.089257,{"lines":{"7":[["Calculating dependencies ",{}],["        ",{"fg":2,"bold":true}],["              ",{"fg":2}],["                                   ",{}]]},"cursor":{"x":33}}],[0.052303,{"lines":{"7":[["Calculating dependencies ",{}],["        R",{"fg":2,"bold":true}],["             ",{"fg":2}],["                                   ",{}]]},"cursor":{"x":34}}],[0.053947,{"lines":{"7":[["Calculating dependencies ",{}],["         o",{"fg":2,"bold":true}],["            ",{"fg":2}],["                                   ",{}]]},"cursor":{"x":35}}],[0.051208,{"lines":{"7":[["Calculating dependencies ",{}],["          c",{"fg":2,"bold":true}],["           ",{"fg":2}],["                                   ",{}]]},"cursor":{"x":36}}],[0.050496,{"lines":{"7":[["Calculating dependencies ",{}],["           k",{"fg":2,"bold":true}],["          ",{"fg":2}],["                                   ",{}]]},"cursor":{"x":37}}],[0.05141,{"lines":{"7":[["Calculating dependencies ",{}],["            s",{"fg":2,"bold":true}],["         ",{"fg":2}],["                                   ",{}]]},"cursor":{"x":38}}],[0.053185,{"lines":{"7":[["Calculating dependencies ",{}],["              ",{"fg":2,"bold":true}],["        ",{"fg":2}],["                                   ",{}]]},"cursor":{"x":39}}],[0.05062,{"lines":{"7":[["Calculating dependencies ",{}],["              (",{"fg":2,"bold":true}],["       ",{"fg":2}],["                                   ",{}]]},"cursor":{"x":40}}],[0.050089,{"lines":{"7":[["Calculating dependencies ",{}],["               L",{"fg":2,"bold":true}],["      ",{"fg":2}],["                                   ",{}]]},"cursor":{"x":41}}],[0.050616,{"lines":{"7":[["Calculating dependencies ",{}],["                i",{"fg":2,"bold":true}],["     ",{"fg":2}],["                                   ",{}]]},"cursor":{"x":42}}],[0.053482,{"lines":{"7":[["Calculating dependencies ",{}],["                 n",{"fg":2,"bold":true}],["    ",{"fg":2}],["                                   ",{}]]},"cursor":{"x":43}}],[0.050445,{"lines":{"7":[["Calculating dependencies ",{}],["                  u",{"fg":2,"bold":true}],["   ",{"fg":2}],["                                   ",{}]]},"cursor":{"x":44}}],[0.050476,{"lines":{"7":[["Calculating dependencies ",{}],["                   x",{"fg":2,"bold":true}],["  ",{"fg":2}],["                                   ",{}]]},"cursor":{"x":45}}],[0.053226,{"lines":{"7":[["Calculating dependencies ",{}],["                    )",{"fg":2,"bold":true}],[" ",{"fg":2}],["                                   ",{}]]},"cursor":{"x":46}}],[0.052588,{"lines":{"7":[["Calculating dependencies ",{}],["                   ",{"fg":2,"bold":true}],[")",{"fg":2}],[")",{"fg":2,"bold":true}],[" ",{"fg":2}],["                                   ",{}]]},"cursor":{"x":45}}],[0.05094,{"lines":{"7":[["Calculating dependencies ",{}],["                  ",{"fg":2,"bold":true}],["x)  ",{"fg":2}],["                                   ",{}]]},"cursor":{"x":44}}],[0.051747,{"lines":{"7":[["Calculating dependencies ",{}],["                 ",{"fg":2,"bold":true}],["ux   ",{"fg":2}],["                                   ",{}]]},"cursor":{"x":43}}],[0.050186,{"lines":{"7":[["Calculating dependencies ",{}],["                ",{"fg":2,"bold":true}],["nu    ",{"fg":2}],["                                   ",{}]]},"cursor":{"x":42}}],[0.050782,{"lines":{"7":[["Calculating dependencies ",{}],["               ",{"fg":2,"bold":true}],["in     ",{"fg":2}],["                                   ",{}]]},"cursor":{"x":41}}],[0.050146,{"lines":{"7":[["Calculating dependencies ",{}],["              ",{"fg":2,"bold":true}],["Li      ",{"fg":2}],["                                   ",{}]]},"cursor":{"x":40}}],[0.051386,{"lines":{"7":[["Calculating dependencies ",{}],["             ",{"fg":2,"bold":true}],["(L       ",{"fg":2}],["                                   ",{}]]},"cursor":{"x":39}}],[0.051571,{"lines":{"7":[["Calculating dependencies ",{}],["            ",{"fg":2,"bold":true}],[" (        ",{"fg":2}],["                                   ",{}]]},"cursor":{"x":38}}],[0.0528,{"lines":{"7":[["Calculating dependencies ",{}],["           ",{"fg":2,"bold":true}],["s          ",{"fg":2}],["                                   ",{}]]},"cursor":{"x":37}}],[0.050345,{"lines":{"7":[["Calculating dependencies ",{}],["          ",{"fg":2,"bold":true}],["ks          ",{"fg":2}],["                                   ",{}]]},"cursor":{"x":36}}],[0.051161,{"lines":{"7":[["Calculating dependencies ",{}],["         ",{"fg":2,"bold":true}],["ck           ",{"fg":2}],["                                   ",{}]]},"cursor":{"x":35}}],[0.053431,{"lines":{"7":[["Calculating dependencies ",{}],["        ",{"fg":2,"bold":true}],["oc            ",{"fg":2}],["                                   ",{}]]},"cursor":{"x":34}}],[0.052697,{"lines":{"7":[["Calculating dependencies ",{}],["       ",{"fg":2,"bold":true}],["Ro             ",{"fg":2}],["                                   ",{}]]},"cursor":{"x":33}}],[0.050466,{"lines":{"7":[["Calculating dependencies ",{}],["      ",{"fg":2,"bold":true}],[" R              ",{"fg":2}],["                                   ",{}]]},"cursor":{"x":32}}],[0.05056,{"lines":{"7":[["Calculating dependencies ",{}],["     ",{"fg":2,"bold":true}],["o                ",{"fg":2}],["                                   ",{}]]},"cursor":{"x":31}}],[0.072838,{"lines":{"7":[["Calculating dependencies ",{}],["    ",{"fg":2,"bold":true}],["oo                ",{"fg":2}],["                                   ",{}]]},"cursor":{"x":30}}],[0.050244,{"lines":{"7":[["Calculating dependencies ",{}],["   ",{"fg":2,"bold":true}],["to                 ",{"fg":2}],["                                   ",{}]]},"cursor":{"x":29}}],[0.050898,{"lines":{"7":[["Calculating dependencies ",{}],["  ",{"fg":2,"bold":true}],["nt                  ",{"fg":2}],["                                   ",{}]]},"cursor":{"x":28}}],[0.050815,{"lines":{"7":[["Calculating dependencies ",{}],[" ",{"fg":2,"bold":true}],["en                   ",{"fg":2}],["                                   ",{}]]},"cursor":{"x":27}}],[0.050437,{"lines":{"7":[["Calculating dependencies ",{}],["Ge                    ",{"fg":2}],["                                   ",{}]]},"cursor":{"x":26}}],[0.050009,{"lines":{"7":[["Calculating dependencies ",{}],[" G",{"fg":2,"bold":true}],["                    ",{"fg":2}],["                                   ",{}]]},"cursor":{"x":27}}],[0.136128,{"lines":{"7":[["Calculating dependencies ",{}],["  e",{"fg":2,"bold":true}],["                   ",{"fg":2}],["                                   ",{}]]},"cursor":{"x":28}}],[0.000134,{"lines":{"7":[["Calculating dependencies ",{}],[" ",{"fg":2,"bold":true}],["... done!",{}],["            ",{"fg":2}],["                                   ",{}]]},"cursor":{"x":0,"y":8}}],[0.026575,{"lines":{"8":[["[",{}],["ebuild",{"fg":2,"bold":true}],["  ",{}],["N",{"fg":2,"bold":true}],["     ] ",{}],["net-im/wineqq-20121221::gentoo-zh",{"fg":2,"bold":true}],["  152,862 kB                    ",{}]],"10":[["Total: 1 package (1 new), Size of downloads: 152,862 kB                           ",{}]]},"cursor":{"y":11}}],[0.000171,{"lines":{"12":[["Would you like to merge these packages?",{"bold":true}],[" [",{}],["Yes",{"fg":2,"bold":true}],["/",{}],["No",{"fg":1,"bold":true}],["]                                  ",{}]]},"cursor":{"x":49,"y":12}}],[2.422122,{"cursor":{"x":0,"y":13}}],[0.102694,{"lines":{"14":[[">>> Verifying ebuild manifests                                                    ",{}]]},"cursor":{"y":15}}],[0.011831,{"lines":{"16":[[">>> Emerging (",{}],["1",{"fg":3,"bold":true}],[" of ",{}],["1",{"fg":3,"bold":true}],[") ",{}],["net-im/wineqq-20121221",{"fg":2}],[" from gentoo-zh                       ",{}]]},"cursor":{"y":17}}],[0.005754,{}],[0.131975,{"lines":{"17":[[">>> Resuming download...                                                          ",{}]]},"cursor":{"y":18}}],[0.000661,{"lines":{"18":[[">>> Downloading 'http://www.longene.org/download/WineQQ2012-20121221-Longene.deb' ",{}]]},"cursor":{"y":19}}],[0.022639,{"lines":{"0":[["密码：                                                                            ",{}]],"1":[["Sorry, try again.                                                                 ",{}]],"2":[["密码：                                                                            ",{}]],"3":[["                                                                                  ",{}]],"4":[["These are the packages that would be merged, in order:",{"fg":2}],["                            ",{}]],"5":[["                                                                                  ",{}]],"6":[["Calculating dependencies ",{}],[" ",{"fg":2,"bold":true}],["... done!",{}],["            ",{"fg":2}],["                                   ",{}]],"7":[["[",{}],["ebuild",{"fg":2,"bold":true}],["  ",{}],["N",{"fg":2,"bold":true}],["     ] ",{}],["net-im/wineqq-20121221::gentoo-zh",{"fg":2,"bold":true}],["  152,862 kB                    ",{}]],"8":[["                                                                                  ",{}]],"9":[["Total: 1 package (1 new), Size of downloads: 152,862 kB                           ",{}]],"10":[["                                                                                  ",{}]],"11":[["Would you like to merge these packages?",{"bold":true}],[" [",{}],["Yes",{"fg":2,"bold":true}],["/",{}],["No",{"fg":1,"bold":true}],["]                                  ",{}]],"12":[["                                                                                  ",{}]],"13":[[">>> Verifying ebuild manifests                                                    ",{}]],"14":[["                                                                                  ",{}]],"15":[[">>> Emerging (",{}],["1",{"fg":3,"bold":true}],[" of ",{}],["1",{"fg":3,"bold":true}],[") ",{}],["net-im/wineqq-20121221",{"fg":2}],[" from gentoo-zh                       ",{}]],"16":[[">>> Resuming download...                                                          ",{}]],"17":[[">>> Downloading 'http://www.longene.org/download/WineQQ2012-20121221-Longene.deb' ",{}]],"18":[["--2013-03-08 20:18:20--  http://www.longene.org/download/WineQQ2012-20121221-Longe",{}]],"19":[["ne.deb                                                                            ",{}]],"20":[["正在解析主机 www.longene.org...                                                   ",{}]]},"cursor":{"x":32,"y":20}}],[0.302309,{"lines":{"0":[["Sorry, try again.                                                                 ",{}]],"1":[["密码：                                                                            ",{}]],"2":[["                                                                                  ",{}]],"3":[["These are the packages that would be merged, in order:",{"fg":2}],["                            ",{}]],"4":[["                                                                                  ",{}]],"5":[["Calculating dependencies ",{}],[" ",{"fg":2,"bold":true}],["... done!",{}],["            ",{"fg":2}],["                                   ",{}]],"6":[["[",{}],["ebuild",{"fg":2,"bold":true}],["  ",{}],["N",{"fg":2,"bold":true}],["     ] ",{}],["net-im/wineqq-20121221::gentoo-zh",{"fg":2,"bold":true}],["  152,862 kB                    ",{}]],"7":[["                                                                                  ",{}]],"8":[["Total: 1 package (1 new), Size of downloads: 152,862 kB                           ",{}]],"9":[["                                                                                  ",{}]],"10":[["Would you like to merge these packages?",{"bold":true}],[" [",{}],["Yes",{"fg":2,"bold":true}],["/",{}],["No",{"fg":1,"bold":true}],["]                                  ",{}]],"11":[["                                                                                  ",{}]],"12":[[">>> Verifying ebuild manifests                                                    ",{}]],"13":[["                                                                                  ",{}]],"14":[[">>> Emerging (",{}],["1",{"fg":3,"bold":true}],[" of ",{}],["1",{"fg":3,"bold":true}],[") ",{}],["net-im/wineqq-20121221",{"fg":2}],[" from gentoo-zh                       ",{}]],"15":[[">>> Resuming download...                                                          ",{}]],"16":[[">>> Downloading 'http://www.longene.org/download/WineQQ2012-20121221-Longene.deb' ",{}]],"17":[["--2013-03-08 20:18:20--  http://www.longene.org/download/WineQQ2012-20121221-Longe",{}]],"18":[["ne.deb                                                                            ",{}]],"19":[["正在解析主机 www.longene.org... 115.236.90.244                                    ",{}]],"20":[["正在连接 www.longene.org|115.236.90.244|:80...                                    ",{}]]},"cursor":{"x":47}}],[0.123415,{"lines":{"0":[["密码：                                                                            ",{}]],"1":[["                                                                                  ",{}]],"2":[["These are the packages that would be merged, in order:",{"fg":2}],["                            ",{}]],"3":[["                                                                                  ",{}]],"4":[["Calculating dependencies ",{}],[" ",{"fg":2,"bold":true}],["... done!",{}],["            ",{"fg":2}],["                                   ",{}]],"5":[["[",{}],["ebuild",{"fg":2,"bold":true}],["  ",{}],["N",{"fg":2,"bold":true}],["     ] ",{}],["net-im/wineqq-20121221::gentoo-zh",{"fg":2,"bold":true}],["  152,862 kB                    ",{}]],"6":[["                                                                                  ",{}]],"7":[["Total: 1 package (1 new), Size of downloads: 152,862 kB                           ",{}]],"8":[["                                                                                  ",{}]],"9":[["Would you like to merge these packages?",{"bold":true}],[" [",{}],["Yes",{"fg":2,"bold":true}],["/",{}],["No",{"fg":1,"bold":true}],["]                                  ",{}]],"10":[["                                                                                  ",{}]],"11":[[">>> Verifying ebuild manifests                                                    ",{}]],"12":[["                                                                                  ",{}]],"13":[[">>> Emerging (",{}],["1",{"fg":3,"bold":true}],[" of ",{}],["1",{"fg":3,"bold":true}],[") ",{}],["net-im/wineqq-20121221",{"fg":2}],[" from gentoo-zh                       ",{}]],"14":[[">>> Resuming download...                                                          ",{}]],"15":[[">>> Downloading 'http://www.longene.org/download/WineQQ2012-20121221-Longene.deb' ",{}]],"16":[["--2013-03-08 20:18:20--  http://www.longene.org/download/WineQQ2012-20121221-Longe",{}]],"17":[["ne.deb                                                                            ",{}]],"18":[["正在解析主机 www.longene.org... 115.236.90.244                                    ",{}]],"19":[["正在连接 www.longene.org|115.236.90.244|:80... 已连接。                           ",{}]],"20":[["已发出 HTTP 请求，正在等待回应...                                                 ",{}]]},"cursor":{"x":34}}],[0.127437,{"lines":{"0":[["Calculating dependencies ",{}],[" ",{"fg":2,"bold":true}],["... done!",{}],["            ",{"fg":2}],["                                   ",{}]],"1":[["[",{}],["ebuild",{"fg":2,"bold":true}],["  ",{}],["N",{"fg":2,"bold":true}],["     ] ",{}],["net-im/wineqq-20121221::gentoo-zh",{"fg":2,"bold":true}],["  152,862 kB                    ",{}]],"2":[["                                                                                  ",{}]],"3":[["Total: 1 package (1 new), Size of downloads: 152,862 kB                           ",{}]],"4":[["                                                                                  ",{}]],"5":[["Would you like to merge these packages?",{"bold":true}],[" [",{}],["Yes",{"fg":2,"bold":true}],["/",{}],["No",{"fg":1,"bold":true}],["]                                  ",{}]],"7":[[">>> Verifying ebuild manifests                                                    ",{}]],"9":[[">>> Emerging (",{}],["1",{"fg":3,"bold":true}],[" of ",{}],["1",{"fg":3,"bold":true}],[") ",{}],["net-im/wineqq-20121221",{"fg":2}],[" from gentoo-zh                       ",{}]],"10":[[">>> Resuming download...                                                          ",{}]],"11":[[">>> Downloading 'http://www.longene.org/download/WineQQ2012-20121221-Longene.deb' ",{}]],"12":[["--2013-03-08 20:18:20--  http://www.longene.org/download/WineQQ2012-20121221-Longe",{}]],"13":[["ne.deb                                                                            ",{}]],"14":[["正在解析主机 www.longene.org... 115.236.90.244                                    ",{}]],"15":[["正在连接 www.longene.org|115.236.90.244|:80... 已连接。                           ",{}]],"16":[["已发出 HTTP 请求，正在等待回应... 206 Partial Content                             ",{}]],"17":[["长度：157717070 (150M)，剩余 156529726 (149M) [text/plain]                        ",{}]],"18":[["正在保存至: “/home/distfiles/WineQQ2012-20121221-Longene.deb”                     ",{}]],"19":[["                                                                                  ",{}]],"20":[[" 0% [                                       ] 1,187,344   --.-K/s                 ",{}]]},"cursor":{"x":79}}],[0.317607,{"lines":{"20":[[" 0% [                                       ] 1,193,825   19.9KB/s                ",{}]]}}],[0.282225,{"lines":{"20":[[" 0% [                                       ] 1,204,232   27.5KB/s                ",{}]]}}],[0.9004490000000001,{"lines":{"20":[[" 0% [                                       ] 1,215,176   18.1KB/s                ",{}]]}}],[0.214111,{"lines":{"20":[[" 0% [                                       ] 1,232,960   26.0KB/s                ",{}]]}}],[0.254346,{"lines":{"20":[[" 0% [                                       ] 1,261,688   36.9KB/s                ",{}]]}}],[0.202362,{"lines":{"20":[[" 0% [                                       ] 1,299,992   50.7KB/s                ",{}]]}}],[0.202074,{"lines":{"20":[[" 0% [                                       ] 1,336,696   61.5KB/s                ",{}]]}}],[0.200672,{"lines":{"20":[[" 0% [                                       ] 1,385,944   75.4KB/s                ",{}]]}}],[0.203688,{"lines":{"20":[[" 0% [                                       ] 1,442,032   89.5KB/s                ",{}]]}}],[0.204077,{"lines":{"20":[[" 0% [                                       ] 1,489,912   99.1KB/s                ",{}]]}}],[0.203116,{"lines":{"20":[[" 0% [                                       ] 1,533,272    106KB/s 剩余 23m 58s   ",{}]]}}],[1.028627,{"lines":{"20":[[" 0% [                                       ] 1,559,264   86.2KB/s 剩余 29m 29s   ",{}]]}}],[0.9500769999999999,{"lines":{"20":[[" 0% [                                       ] 1,559,264   70.3KB/s 剩余 29m 29s   ",{}]]}}],[0.737437,{"lines":{"20":[[" 0% [                                       ] 1,567,456   62.9KB/s 剩余 40m 24s   ",{}]]}}],[0.951008,{"lines":{"20":[[" 0% [                                       ] 1,570,208   54.6KB/s 剩余 40m 24s   ",{}]]}}],[0.414522,{"lines":{"20":[[" 1% [                                       ] 1,578,400   52.6KB/s 剩余 48m 21s   ",{}]]}}],[0.255809,{"lines":{"20":[[" 1% [                                       ] 1,705,440   67.3KB/s 剩余 48m 21s   ",{}]]}}],[0.251591,{"lines":{"20":[[" 1% [                                       ] 1,750,600   70.8KB/s 剩余 48m 21s   ",{}]]}}],[0.259378,{"lines":{"20":[[" 1% [                                       ] 1,771,120   71.0KB/s 剩余 48m 21s   ",{}]]}}],[0.199964,{"lines":{"20":[[" 1% [                                       ] 1,824,472   75.6KB/s 剩余 48m 21s   ",{}]]}}],[0.218766,{"lines":{"20":[[" 1% [                                       ] 1,855,936   79.5KB/s 剩余 32m 50s   ",{}]]}}],[0.584212,{"lines":{"20":[[" 1% [                                       ] 1,872,336   85.2KB/s 剩余 32m 50s   ",{}]]}}],[0.200233,{"lines":{"20":[[" 1% [                                       ] 1,972,216   96.3KB/s 剩余 32m 50s   ",{}]]}}],[0.203606,{"lines":{"20":[[" 1% [                                       ] 2,028,304   99.9KB/s 剩余 32m 50s   ",{}]]}}],[0.204457,{"lines":{"20":[[" 1% [                                       ] 2,091,232    105KB/s 剩余 27m 41s   ",{}]]}}],[0.244371,{"lines":{"20":[[" 1% [                                       ] 2,140,480    107KB/s 剩余 27m 41s   ",{}]]}}],[0.603341,{"lines":{"20":[[" 1% [                                       ] 2,161,000   95.9KB/s 剩余 27m 41s   ",{}]]}}],[0.3779,{"lines":{"20":[[" 1% [                                       ] 2,171,928   91.2KB/s 剩余 28m 37s   ",{}]]}}],[0.275925,{"lines":{"20":[[" 1% [                                       ] 2,271,808   96.9KB/s 剩余 28m 37s   ",{}]]}}],[0.204996,{"lines":{"20":[[" 1% [                                       ] 2,278,648   92.4KB/s 剩余 28m 37s   ",{}]]}}],[0.229465,{"lines":{"20":[[" 1% [                                       ] 2,303,272    127KB/s 剩余 28m 37s   ",{}]]}}],[0.203566,{"lines":{"20":[[" 1% [                                       ] 2,353,888    168KB/s 剩余 28m 37s   ",{}]]}}],[0.206381,{"lines":{"20":[[" 1% [                                       ] 2,407,240    153KB/s 剩余 25m 27s   ",{}]]}}],[0.21139,{"lines":{"20":[[" 1% [                                       ] 2,451,016    158KB/s 剩余 25m 27s   ",{}]]}}],[0.207634,{"lines":{"20":[[" 1% [                                       ] 2,487,952    161KB/s 剩余 25m 27s   ",{}]]}}],[0.200606,{"lines":{"20":[[" 1% [                                       ] 2,518,048    156KB/s 剩余 25m 27s   ",{}]]}}],[0.200822,{"lines":{"20":[[" 1% [                                       ] 2,557,720    157KB/s 剩余 25m 27s   ",{}]]}}],[0.202241,{"lines":{"20":[[" 1% [                                       ] 2,586,448    175KB/s 剩余 24m 3s    ",{}]]}}],[0.206472,{"lines":{"20":[[" 1% [                                       ] 2,605,600    157KB/s 剩余 24m 3s    ",{}]]}}],[0.204469,{"lines":{"20":[[" 1% [                                       ] 2,650,744    153KB/s 剩余 24m 3s    ",{}]]}}],[0.209707,{"lines":{"20":[[" 1% [                                       ] 2,675,368    139KB/s 剩余 24m 3s    ",{}]]}}],[0.218074,{"lines":{"20":[[" 1% [                                       ] 2,701,360    139KB/s 剩余 24m 3s    ",{}]]}}],[0.223193,{"lines":{"20":[[" 1% [                                       ] 2,717,776    152KB/s 剩余 23m 45s   ",{}]]}}],[0.206835,{"lines":{"20":[[" 1% [                                       ] 2,750,608    171KB/s 剩余 23m 45s   ",{}]]}}],[0.20482,{"lines":{"20":[[" 1% [                                       ] 2,803,960    157KB/s 剩余 23m 45s   ",{}]]}}],[0.208822,{"lines":{"20":[[" 1% [                                       ] 2,843,632    166KB/s 剩余 23m 45s   ",{}]]}}],[0.205515,{"lines":{"20":[[" 1% [                                       ] 2,891,512    168KB/s 剩余 23m 45s   ",{}]]}}],[0.205432,{"lines":{"20":[[" 1% [                                       ] 2,935,288    165KB/s 剩余 22m 18s   ",{}]]}}],[0.202317,{"lines":{"20":[[" 1% [                                       ] 2,974,960    165KB/s 剩余 22m 18s   ",{}]]}}],[0.202049,{"lines":{"20":[[" 1% [                                       ] 3,020,104    168KB/s 剩余 22m 18s   ",{}]]}}],[0.204912,{"lines":{"20":[[" 1% [                                       ] 3,047,464    165KB/s 剩余 22m 18s   ",{}]]}}],[0.213806,{"lines":{"20":[[" 1% [                                       ] 3,080,296    163KB/s 剩余 22m 18s   ",{}]]}}],[1.036649,{"lines":{"20":[[" 1% [                                       ] 3,091,240    125KB/s 剩余 22m 58s   ",{}]]}}],[0.951004,{"lines":{"20":[[" 1% [                                       ] 3,091,240    102KB/s 剩余 22m 58s   ",{}]]}}],[0.951002,{"lines":{"20":[[" 1% [                                       ] 3,091,240   85.7KB/s 剩余 25m 32s   ",{}]]}}],[1.007026,{"lines":{"20":[[" 1% [                                       ] 3,126,792   76.7KB/s 剩余 26m 24s   ",{}]]}}],[0.242602,{"lines":{"20":[[" 1% [                                       ] 3,135,000   73.0KB/s 剩余 26m 24s   ",{}]]}}],[0.338135,{"lines":{"20":[[" 1% [                                       ] 3,148,696   69.0KB/s 剩余 26m 24s   ",{}]]}}],[0.954774,{"lines":{"20":[[" 2% [                                       ] 3,163,744   62.6KB/s 剩余 27m 54s   ",{}]]}}],[0.9509649999999999,{"lines":{"20":[[" 2% [                                       ] 3,163,744   55.9KB/s 剩余 27m 54s   ",{}]]}}],[0.950817,{"lines":{"20":[[" 2% [                                       ] 3,163,744   50.5KB/s 剩余 30m 23s   ",{}]]}}],[0.951163,{"lines":{"20":[[" 2% [                                       ] 3,163,744   46.1KB/s 剩余 30m 23s   ",{}]]}}],[0.951,{"lines":{"20":[[" 2% [                                       ] 3,163,744   42.4KB/s 剩余 32m 52s   ",{}]]}}],[0.202673,{"lines":{"20":[[" 2% [                                       ] 3,167,848   40.9KB/s 剩余 32m 52s   ",{}]]}}],[0.255178,{"lines":{"20":[[" 2% [                                       ] 3,191,104   40.2KB/s 剩余 32m 52s   ",{}]]}}],[0.248581,{"lines":{"20":[[" 2% [                                       ] 3,210,256   40.6KB/s 剩余 32m 52s   ",{}]]}}],[0.220123,{"lines":{"20":[[" 2% [                                       ] 3,218,464   38.8KB/s 剩余 32m 52s   ",{}]]}}],[0.32074,{"lines":{"20":[[" 2% [                                       ] 3,236,248   36.3KB/s 剩余 33m 15s   ",{}]]}}],[0.413605,{"lines":{"20":[[" 2% [                                       ] 3,264,976   30.5KB/s 剩余 33m 15s   ",{}]]}}],[0.213097,{"lines":{"20":[[" 2% [                                       ] 3,290,968   30.1KB/s 剩余 33m 15s   ",{}]]}}],[0.346804,{"lines":{"20":[[" 2% [                                       ] 3,325,168   26.6KB/s 剩余 33m 15s   ",{}]]}}],[0.215262,{"lines":{"20":[[" 2% [                                       ] 3,353,896   26.6KB/s 剩余 32m 50s   ",{}]]}}],[0.212494,{"lines":{"20":[[" 2% [                                       ] 3,381,256   27.4KB/s 剩余 32m 50s   ",{}]]}}],[0.200671,{"lines":{"20":[[" 2% [                                       ] 3,411,352   27.1KB/s 剩余 32m 50s   ",{}]]}}],[0.339099,{"lines":{"20":[[" 2% [                                       ] 3,431,872   34.4KB/s 剩余 32m 50s   ",{}]]}}],[0.327906,{"lines":{"20":[[" 2% [                                       ] 3,449,656   35.6KB/s 剩余 32m 39s   ",{}]]}}],[0.228541,{"lines":{"20":[[" 2% [                                       ] 3,483,856   38.5KB/s 剩余 32m 39s   ",{}]]}}],[0.26991,{"lines":{"20":[[" 2% [                                       ] 3,505,744   39.7KB/s 剩余 32m 39s   ",{}]]}}],[0.251193,{"lines":{"20":[[" 2% [                                       ] 3,526,264   85.4KB/s 剩余 32m 39s   ",{}]]}}],[0.890582,{"lines":{"0":[["Total: 1 package (1 new), Size of downloads: 152,862 kB                           ",{}]],"1":[["                                                                                  ",{}]],"2":[["Would you like to merge these packages?",{"bold":true}],[" [",{}],["Yes",{"fg":2,"bold":true}],["/",{}],["No",{"fg":1,"bold":true}],["]                                  ",{}]],"3":[["                                                                                  ",{}]],"4":[[">>> Verifying ebuild manifests                                                    ",{}]],"5":[["                                                                                  ",{}]],"6":[[">>> Emerging (",{}],["1",{"fg":3,"bold":true}],[" of ",{}],["1",{"fg":3,"bold":true}],[") ",{}],["net-im/wineqq-20121221",{"fg":2}],[" from gentoo-zh                       ",{}]],"7":[[">>> Resuming download...                                                          ",{}]],"8":[[">>> Downloading 'http://www.longene.org/download/WineQQ2012-20121221-Longene.deb' ",{}]],"9":[["--2013-03-08 20:18:20--  http://www.longene.org/download/WineQQ2012-20121221-Longe",{}]],"10":[["ne.deb                                                                            ",{}]],"11":[["正在解析主机 www.longene.org... 115.236.90.244                                    ",{}]],"12":[["正在连接 www.longene.org|115.236.90.244|:80... 已连接。                           ",{}]],"13":[["已发出 HTTP 请求，正在等待回应... 206 Partial Content                             ",{}]],"14":[["长度：157717070 (150M)，剩余 156529726 (149M) [text/plain]                        ",{}]],"15":[["正在保存至: “/home/distfiles/WineQQ2012-20121221-Longene.deb”                     ",{}]],"16":[["                                                                                  ",{}]],"17":[[" 2% [                                       ] 3,526,264   85.4KB/s 剩余 32m 39s^C ",{}]],"18":[["                                                                                  ",{}]],"19":[["Exiting on signal 2                                                               ",{}]],"20":[["                                                                                  ",{}]]},"cursor":{"x":0}}],[0.008451,{"lines":{"0":[[">>> Resuming download...                                                          ",{}]],"1":[[">>> Downloading 'http://www.longene.org/download/WineQQ2012-20121221-Longene.deb' ",{}]],"2":[["--2013-03-08 20:18:20--  http://www.longene.org/download/WineQQ2012-20121221-Longe",{}]],"3":[["ne.deb                                                                            ",{}]],"4":[["正在解析主机 www.longene.org... 115.236.90.244                                    ",{}]],"5":[["正在连接 www.longene.org|115.236.90.244|:80... 已连接。                           ",{}]],"6":[["已发出 HTTP 请求，正在等待回应... 206 Partial Content                             ",{}]],"7":[["长度：157717070 (150M)，剩余 156529726 (149M) [text/plain]                        ",{}]],"8":[["正在保存至: “/home/distfiles/WineQQ2012-20121221-Longene.deb”                     ",{}]],"9":[["                                                                                  ",{}]],"10":[[" 2% [                                       ] 3,526,264   85.4KB/s 剩余 32m 39s^C ",{}]],"11":[["                                                                                  ",{}]],"12":[["Exiting on signal 2                                                               ",{}]],"13":[[" * ",{"fg":1,"bold":true}],["Fetch failed for 'net-im/wineqq-20121221', Log file:                           ",{}]],"14":[[" * ",{"fg":1,"bold":true}],[" '/var/tmp/portage/net-im/wineqq-20121221/temp/build.log'                      ",{}]],"15":[["                                                                                  ",{}]],"16":[[" * ",{"fg":2,"bold":true}],["Messages for package ",{}],["net-im/wineqq-20121221",{"fg":2}],[":                                   ",{}]],"17":[["                                                                                  ",{}]],"18":[[" * ",{"fg":1,"bold":true}],["Fetch failed for 'net-im/wineqq-20121221', Log file:                           ",{}]],"19":[[" * ",{"fg":1,"bold":true}],[" '/var/tmp/portage/net-im/wineqq-20121221/temp/build.log'                      ",{}]]}}],[0.113744,{"lines":{"20":[["cai@gentoo",{"fg":2,"bold":true}],[" ~ $",{"fg":4,"bold":true}],["                                                                    ",{}]]},"cursor":{"x":15}}],[0.629837,{"lines":{"0":[[">>> Downloading 'http://www.longene.org/download/WineQQ2012-20121221-Longene.deb' ",{}]],"1":[["--2013-03-08 20:18:20--  http://www.longene.org/download/WineQQ2012-20121221-Longe",{}]],"2":[["ne.deb                                                                            ",{}]],"3":[["正在解析主机 www.longene.org... 115.236.90.244                                    ",{}]],"4":[["正在连接 www.longene.org|115.236.90.244|:80... 已连接。                           ",{}]],"5":[["已发出 HTTP 请求，正在等待回应... 206 Partial Content                             ",{}]],"6":[["长度：157717070 (150M)，剩余 156529726 (149M) [text/plain]                        ",{}]],"7":[["正在保存至: “/home/distfiles/WineQQ2012-20121221-Longene.deb”                     ",{}]],"8":[["                                                                                  ",{}]],"9":[[" 2% [                                       ] 3,526,264   85.4KB/s 剩余 32m 39s^C ",{}]],"10":[["                                                                                  ",{}]],"11":[["Exiting on signal 2                                                               ",{}]],"12":[[" * ",{"fg":1,"bold":true}],["Fetch failed for 'net-im/wineqq-20121221', Log file:                           ",{}]],"13":[[" * ",{"fg":1,"bold":true}],[" '/var/tmp/portage/net-im/wineqq-20121221/temp/build.log'                      ",{}]],"14":[["                                                                                  ",{}]],"15":[[" * ",{"fg":2,"bold":true}],["Messages for package ",{}],["net-im/wineqq-20121221",{"fg":2}],[":                                   ",{}]],"16":[["                                                                                  ",{}]],"17":[[" * ",{"fg":1,"bold":true}],["Fetch failed for 'net-im/wineqq-20121221', Log file:                           ",{}]],"18":[[" * ",{"fg":1,"bold":true}],[" '/var/tmp/portage/net-im/wineqq-20121221/temp/build.log'                      ",{}]],"19":[["cai@gentoo",{"fg":2,"bold":true}],[" ~ $",{"fg":4,"bold":true}],[" exit                                                               ",{}]],"20":[["                                                                                  ",{}]]},"cursor":{"x":0}}]]